CHANGELOG
COPYING
COPYING.LESSER
MANIFEST.in
README
setup.py
LiteroticAPI.egg-info/PKG-INFO
LiteroticAPI.egg-info/SOURCES.txt
LiteroticAPI.egg-info/dependency_links.txt
LiteroticAPI.egg-info/requires.txt
LiteroticAPI.egg-info/top_level.txt
literoticapi/__init__.py
literoticapi/author.py
literoticapi/story.py