Metadata-Version: 1.0
Name: LiteroticAPI
Version: 0.1.1
Summary: an API for Literotica
Home-page: http://hrroon.github.com/LiteroticAPI
Author: hrroon
Author-email: UNKNOWN
License: LGPL
Platform: UNKNOWN
